{"intId":"7d497b9b0038b3264065a9c130f29f795137fb05-1665552508212","extId":"19042111356d2b710456f912e9e5dd9c9f1fca6b-1224-1337[2802]","name":"Ahasan#ADMC_2 (ADMC_2)","users":{"2648-1":{"userKey":"2648-1","extId":"2648","intIds":{"w_w4yxx02uo7ic":{"intId":"w_w4yxx02uo7ic","registeredOn":1665555139307,"leftOn":1665557913232,"userLeftFlag":true},"w_1ne26i6hulby":{"intId":"w_1ne26i6hulby","registeredOn":1665558095750,"leftOn":1665562233233,"userLeftFlag":true},"w_glyuyceaiexj":{"intId":"w_glyuyceaiexj","registeredOn":1665562258743,"leftOn":1665569843233,"userLeftFlag":true}},"name":"Potjanee KLAITHIN","isModerator":false,"isDialIn":false,"answers":{},"talk":{"totalTime":0,"lastTalkStartedOn":0},"emojis":[],"webcams":[],"totalOfMessages":1},"3214-1":{"userKey":"3214-1","extId":"3214","intIds":{"w_k0ghqlwg8geq":{"intId":"w_k0ghqlwg8geq","registeredOn":1665553516043,"leftOn":1665560033232,"userLeftFlag":true},"w_w41fzlf79pvz":{"intId":"w_w41fzlf79pvz","registeredOn":1665565232753,"leftOn":1665567663233,"userLeftFlag":true}},"name":"Tanatchaya MAYER","isModerator":false,"isDialIn":false,"answers":{},"talk":{"totalTime":0,"lastTalkStartedOn":0},"emojis":[],"webcams":[],"totalOfMessages":1},"2871-1":{"userKey":"2871-1","extId":"2871","intIds":{"w_fhmiaskasz8q":{"intId":"w_fhmiaskasz8q","registeredOn":1665564520940,"leftOn":1665569173232,"userLeftFlag":true},"w_cwvvxwxgtwqd":{"intId":"w_cwvvxwxgtwqd","registeredOn":1665564305673,"leftOn":1665564503233,"userLeftFlag":true},"w_1anvucwauxuo":{"intId":"w_1anvucwauxuo","registeredOn":1665554573245,"leftOn":1665558073232,"userLeftFlag":true},"w_5zflf1t5xgnr":{"intId":"w_5zflf1t5xgnr","registeredOn":1665553664975,"leftOn":1665554573232,"userLeftFlag":true},"w_qbv2mnbcrtdx":{"intId":"w_qbv2mnbcrtdx","registeredOn":1665569172081,"leftOn":1665569733232,"userLeftFlag":true},"w_eob1pper8zo4":{"intId":"w_eob1pper8zo4","registeredOn":1665558062443,"leftOn":1665564313233,"userLeftFlag":true}},"name":"Hien My TRAN","isModerator":false,"isDialIn":false,"answers":{},"talk":{"totalTime":0,"lastTalkStartedOn":0},"emojis":[],"webcams":[],"totalOfMessages":1},"3165-1":{"userKey":"3165-1","extId":"3165","intIds":{"w_3lajebak9ykc":{"intId":"w_3lajebak9ykc","registeredOn":1665553022112,"leftOn":1665553163233,"userLeftFlag":true},"w_jmdtl4h1qbcx":{"intId":"w_jmdtl4h1qbcx","registeredOn":1665553156045,"leftOn":1665553383232,"userLeftFlag":true},"w_x2b8c5wzlj0d":{"intId":"w_x2b8c5wzlj0d","registeredOn":1665553386347,"leftOn":1665557483232,"userLeftFlag":true}},"name":"Pornrita PHOOLSAP","isModerator":false,"isDialIn":false,"answers":{},"talk":{"totalTime":0,"lastTalkStartedOn":0},"emojis":[],"webcams":[],"totalOfMessages":1},"3119-1":{"userKey":"3119-1","extId":"3119","intIds":{"w_wglgswetbmgc":{"intId":"w_wglgswetbmgc","registeredOn":1665553788686,"leftOn":1665554373233,"userLeftFlag":true},"w_2bzlwngdvuiy":{"intId":"w_2bzlwngdvuiy","registeredOn":1665554362065,"leftOn":1665555623233,"userLeftFlag":true},"w_vketqwtceg2t":{"intId":"w_vketqwtceg2t","registeredOn":1665557097434,"leftOn":1665560903232,"userLeftFlag":true}},"name":"Supachai BUACHUEN","isModerator":false,"isDialIn":false,"answers":{},"talk":{"totalTime":0,"lastTalkStartedOn":0},"emojis":[],"webcams":[],"totalOfMessages":1},"3606-1":{"userKey":"3606-1","extId":"3606","intIds":{"w_af32aclcnoes":{"intId":"w_af32aclcnoes","registeredOn":1665552668937,"leftOn":1665553853232,"userLeftFlag":true}},"name":"Ailada KITTIAMORNDEJA","isModerator":false,"isDialIn":false,"answers":{},"talk":{"totalTime":0,"lastTalkStartedOn":0},"emojis":[],"webcams":[],"totalOfMessages":1},"3622-1":{"userKey":"3622-1","extId":"3622","intIds":{"w_o7htf0vfqdgd":{"intId":"w_o7htf0vfqdgd","registeredOn":1665556220265,"leftOn":1665571525181,"userLeftFlag":false}},"name":"Paveena KONYUEN","isModerator":false,"isDialIn":false,"answers":{},"talk":{"totalTime":0,"lastTalkStartedOn":0},"emojis":[],"webcams":[],"totalOfMessages":1},"3141-1":{"userKey":"3141-1","extId":"3141","intIds":{"w_dxwlvumr9r3i":{"intId":"w_dxwlvumr9r3i","registeredOn":1665565703529,"leftOn":1665566203222,"userLeftFlag":true},"w_ab5wysntapaa":{"intId":"w_ab5wysntapaa","registeredOn":1665557706340,"leftOn":1665564943232,"userLeftFlag":true},"w_8jhdvwokqp3q":{"intId":"w_8jhdvwokqp3q","registeredOn":1665555667039,"leftOn":1665557703233,"userLeftFlag":true},"w_gdwaqoxutxrd":{"intId":"w_gdwaqoxutxrd","registeredOn":1665565059352,"leftOn":1665565153232,"userLeftFlag":true},"w_vfytjjwgyp9g":{"intId":"w_vfytjjwgyp9g","registeredOn":1665555596343,"leftOn":1665555683233,"userLeftFlag":true},"w_jdfwcwqrn4eb":{"intId":"w_jdfwcwqrn4eb","registeredOn":1665566359025,"leftOn":1665569523232,"userLeftFlag":true}},"name":"Kittichai PUNDEEKA","isModerator":false,"isDialIn":false,"answers":{},"talk":{"totalTime":0,"lastTalkStartedOn":0},"emojis":[],"webcams":[],"totalOfMessages":2},"1841-1":{"userKey":"1841-1","extId":"1841","intIds":{"w_chvar4y95p8s":{"intId":"w_chvar4y95p8s","registeredOn":1665553937826,"leftOn":1665565173232,"userLeftFlag":true},"w_kd6sa3sc3tth":{"intId":"w_kd6sa3sc3tth","registeredOn":1665565163604,"leftOn":1665565683233,"userLeftFlag":true},"w_3sy0j63qiipu":{"intId":"w_3sy0j63qiipu","registeredOn":1665565751776,"leftOn":1665567743232,"userLeftFlag":true}},"name":"Sukanya BUDTHO","isModerator":false,"isDialIn":false,"answers":{},"talk":{"totalTime":0,"lastTalkStartedOn":0},"emojis":[],"webcams":[],"totalOfMessages":1},"3600-2":{"userKey":"3600-2","extId":"3600","intIds":{"w_3qd87ujspbiw":{"intId":"w_3qd87ujspbiw","registeredOn":1665569902571,"leftOn":1665571525181,"userLeftFlag":false}},"name":"Thritsawan BUNMA","isModerator":false,"isDialIn":false,"answers":{},"talk":{"totalTime":0,"lastTalkStartedOn":0},"emojis":[],"webcams":[],"totalOfMessages":0},"296-1":{"userKey":"296-1","extId":"296","intIds":{"w_duaucuixiusy":{"intId":"w_duaucuixiusy","registeredOn":1665558615997,"leftOn":1665570733232,"userLeftFlag":true}},"name":"Wiphakorn SONGSERM","isModerator":false,"isDialIn":false,"answers":{},"talk":{"totalTime":0,"lastTalkStartedOn":0},"emojis":[],"webcams":[],"totalOfMessages":1},"3597-1":{"userKey":"3597-1","extId":"3597","intIds":{"w_uvpzw7v0f3jj":{"intId":"w_uvpzw7v0f3jj","registeredOn":1665554207229,"leftOn":1665554593232,"userLeftFlag":true}},"name":"Jutamas BUNCHAROEN","isModerator":false,"isDialIn":false,"answers":{},"talk":{"totalTime":0,"lastTalkStartedOn":0},"emojis":[],"webcams":[],"totalOfMessages":1},"3600-1":{"userKey":"3600-1","extId":"3600","intIds":{"w_hy6y1vncfu21":{"intId":"w_hy6y1vncfu21","registeredOn":1665554311633,"leftOn":1665560083232,"userLeftFlag":true},"w_ppgum5xaualo":{"intId":"w_ppgum5xaualo","registeredOn":1665560086746,"leftOn":1665571525181,"userLeftFlag":false}},"name":"Thritsawan BUNMA","isModerator":false,"isDialIn":false,"answers":{},"talk":{"totalTime":0,"lastTalkStartedOn":0},"emojis":[],"webcams":[],"totalOfMessages":1},"2928-1":{"userKey":"2928-1","extId":"2928","intIds":{"w_idboc6catbnl":{"intId":"w_idboc6catbnl","registeredOn":1665563631244,"leftOn":1665563813233,"userLeftFlag":true}},"name":"Hai Yen HO","isModerator":false,"isDialIn":false,"answers":{},"talk":{"totalTime":0,"lastTalkStartedOn":0},"emojis":[],"webcams":[],"totalOfMessages":2},"385-1":{"userKey":"385-1","extId":"385","intIds":{"w_dmidafilgdte":{"intId":"w_dmidafilgdte","registeredOn":1665553527369,"leftOn":1665555633223,"userLeftFlag":true},"w_uhp6zfqkhcq3":{"intId":"w_uhp6zfqkhcq3","registeredOn":1665560360133,"leftOn":1665560373232,"userLeftFlag":true},"w_f1lsfpbhz4lg":{"intId":"w_f1lsfpbhz4lg","registeredOn":1665560400083,"leftOn":1665566553233,"userLeftFlag":true}},"name":"Nattanicha WATTANAFUNGCHAROEN","isModerator":false,"isDialIn":false,"answers":{},"talk":{"totalTime":0,"lastTalkStartedOn":0},"emojis":[],"webcams":[],"totalOfMessages":1},"9-1":{"userKey":"9-1","extId":"9","intIds":{"w_1w3twabetnxu":{"intId":"w_1w3twabetnxu","registeredOn":1665553212013,"leftOn":1665571525181,"userLeftFlag":false}},"name":"Masrur Ahasan","isModerator":true,"isDialIn":false,"answers":{},"talk":{"totalTime":1954828,"lastTalkStartedOn":0},"emojis":[],"webcams":[],"totalOfMessages":13},"3601-1":{"userKey":"3601-1","extId":"3601","intIds":{"w_vr9bdrtnklss":{"intId":"w_vr9bdrtnklss","registeredOn":1665557979378,"leftOn":1665565353232,"userLeftFlag":true}},"name":"Napatsaporn CHAO-UTHAI","isModerator":false,"isDialIn":false,"answers":{},"talk":{"totalTime":0,"lastTalkStartedOn":0},"emojis":[],"webcams":[],"totalOfMessages":1},"2429-1":{"userKey":"2429-1","extId":"2429","intIds":{"w_3ktx2msdfkbh":{"intId":"w_3ktx2msdfkbh","registeredOn":1665556182830,"leftOn":1665557963232,"userLeftFlag":true},"w_x4vbwran7qrs":{"intId":"w_x4vbwran7qrs","registeredOn":1665557978500,"leftOn":1665558983232,"userLeftFlag":true},"w_a038vsis2cio":{"intId":"w_a038vsis2cio","registeredOn":1665559107957,"leftOn":1665571525181,"userLeftFlag":false}},"name":"Thi Hai Yen TRAN","isModerator":false,"isDialIn":false,"answers":{},"talk":{"totalTime":0,"lastTalkStartedOn":0},"emojis":[],"webcams":[],"totalOfMessages":1},"3607-1":{"userKey":"3607-1","extId":"3607","intIds":{"w_qkzusuordlns":{"intId":"w_qkzusuordlns","registeredOn":1665556399757,"leftOn":1665571525181,"userLeftFlag":false}},"name":"Praipaka CHANSUWAN","isModerator":false,"isDialIn":false,"answers":{},"talk":{"totalTime":0,"lastTalkStartedOn":0},"emojis":[],"webcams":[],"totalOfMessages":1},"385-2":{"userKey":"385-2","extId":"385","intIds":{"w_uhp6zfqkhcq3":{"intId":"w_uhp6zfqkhcq3","registeredOn":1665555594230,"leftOn":1665560023232,"userLeftFlag":true}},"name":"Nattanicha WATTANAFUNGCHAROEN","isModerator":false,"isDialIn":false,"answers":{},"talk":{"totalTime":0,"lastTalkStartedOn":0},"emojis":[],"webcams":[],"totalOfMessages":0},"3131-1":{"userKey":"3131-1","extId":"3131","intIds":{"w_cm3xioyxlpzx":{"intId":"w_cm3xioyxlpzx","registeredOn":1665562781097,"leftOn":1665562823232,"userLeftFlag":true}},"name":"Quoc Nam TRAN","isModerator":false,"isDialIn":false,"answers":{},"talk":{"totalTime":0,"lastTalkStartedOn":0},"emojis":[],"webcams":[],"totalOfMessages":1},"1533-1":{"userKey":"1533-1","extId":"1533","intIds":{"w_byto3vvkg6aa":{"intId":"w_byto3vvkg6aa","registeredOn":1665553191408,"leftOn":1665554783233,"userLeftFlag":true}},"name":"Nisanart ORANIN","isModerator":false,"isDialIn":false,"answers":{},"talk":{"totalTime":0,"lastTalkStartedOn":0},"emojis":[],"webcams":[],"totalOfMessages":1},"3059-1":{"userKey":"3059-1","extId":"3059","intIds":{"w_mnqmai6svy8u":{"intId":"w_mnqmai6svy8u","registeredOn":1665552511623,"leftOn":1665566983232,"userLeftFlag":true},"w_y9mkiqwj5wv4":{"intId":"w_y9mkiqwj5wv4","registeredOn":1665566998007,"leftOn":1665570703232,"userLeftFlag":true}},"name":"Jirassaya SAE SONG","isModerator":false,"isDialIn":false,"answers":{},"talk":{"totalTime":0,"lastTalkStartedOn":0},"emojis":[],"webcams":[],"totalOfMessages":1},"3324-1":{"userKey":"3324-1","extId":"3324","intIds":{"w_ry6dhxgoreoz":{"intId":"w_ry6dhxgoreoz","registeredOn":1665570118211,"leftOn":1665570183232,"userLeftFlag":true}},"name":"Thi Thuy DO","isModerator":false,"isDialIn":false,"answers":{},"talk":{"totalTime":0,"lastTalkStartedOn":0},"emojis":[],"webcams":[],"totalOfMessages":1},"3612-1":{"userKey":"3612-1","extId":"3612","intIds":{"w_f9xd5hmtka9z":{"intId":"w_f9xd5hmtka9z","registeredOn":1665555825246,"leftOn":1665560783232,"userLeftFlag":true}},"name":"Pornthawee PUKPANAN","isModerator":false,"isDialIn":false,"answers":{},"talk":{"totalTime":0,"lastTalkStartedOn":0},"emojis":[],"webcams":[],"totalOfMessages":1},"3318-1":{"userKey":"3318-1","extId":"3318","intIds":{"w_8gcacid0551s":{"intId":"w_8gcacid0551s","registeredOn":1665554938713,"leftOn":1665569893232,"userLeftFlag":true}},"name":"Aparecida Mayumi SANTOS TENGAN","isModerator":false,"isDialIn":false,"answers":{},"talk":{"totalTime":0,"lastTalkStartedOn":0},"emojis":[],"webcams":[],"totalOfMessages":1},"3599-1":{"userKey":"3599-1","extId":"3599","intIds":{"w_lfmtluozrtw7":{"intId":"w_lfmtluozrtw7","registeredOn":1665560259053,"leftOn":1665569783232,"userLeftFlag":true}},"name":"Kuakao KHAMMABOOT","isModerator":false,"isDialIn":false,"answers":{},"talk":{"totalTime":0,"lastTalkStartedOn":0},"emojis":[],"webcams":[],"totalOfMessages":1}},"polls":{},"screenshares":[],"presentationSlides":[{"presentationId":"abf6d82ec85cd4e8365d37d7197f64def500ac12-1665552508216","pageNum":1,"setOn":1665552514121}],"createdOn":1665552508218,"endedOn":1665571525181}