{"intId":"53a9ae3d9631e44994f412572b1eb21ae5385e29-1667728109100","extId":"9964543434e35175b9e435fd2fcb2b7a8f8aea76-1224-1339[2801]","name":"Virtual Class - ADMC1 and ADMC01 - Mehedi (ADMC_01)","users":{"3113-1":{"userKey":"3113-1","extId":"3113","intIds":{"w_zrsjrblzocnk":{"intId":"w_zrsjrblzocnk","registeredOn":1667728110747,"leftOn":1667728134122,"userLeftFlag":true}},"name":"Thi My Hanh TRAN","isModerator":false,"isDialIn":false,"answers":{},"talk":{"totalTime":0,"lastTalkStartedOn":0},"emojis":[],"webcams":[],"totalOfMessages":0}},"polls":{},"screenshares":[],"presentationSlides":[{"presentationId":"7a8e9f4302144b9a17a70f65dcedbb15927c1ff4-1667728109101","pageNum":1,"setOn":1667728114427}],"createdOn":1667728109102,"endedOn":1667728194123}