{"intId":"0bc106c4911af15340b07b40ae03130cc685e83c-1669847711936","extId":"615d117eeba41ce2569ff9c1bbf881d32d3134ea-1146-1252","name":"Virtual Class FSKWTG006 Calvin Zhan","users":{"3916-1":{"userKey":"3916-1","extId":"3916","intIds":{"w_n2j1pudfptyr":{"intId":"w_n2j1pudfptyr","registeredOn":1669847713512,"leftOn":1669849179575,"userLeftFlag":false}},"name":"Wan Hao LAI","isModerator":false,"isDialIn":false,"answers":{},"talk":{"totalTime":0,"lastTalkStartedOn":0},"emojis":[],"webcams":[],"totalOfMessages":2},"2720-1":{"userKey":"2720-1","extId":"2720","intIds":{"w_1lolrsmzuzq0":{"intId":"w_1lolrsmzuzq0","registeredOn":1669849006662,"leftOn":1669849179575,"userLeftFlag":false}},"name":"Calvin Zhan","isModerator":true,"isDialIn":false,"answers":{},"talk":{"totalTime":0,"lastTalkStartedOn":0},"emojis":[],"webcams":[],"totalOfMessages":0}},"polls":{},"screenshares":[],"presentationSlides":[{"presentationId":"30a865e55918dfea7fa78704987e54d700c408fd-1669847711939","pageNum":1,"setOn":1669847717353}],"createdOn":1669847711940,"endedOn":1669849179575}