{"intId":"24d78d2530e0e032c2564253f5fc3a3a8a666929-1665959787069","extId":"9964543434e35175b9e435fd2fcb2b7a8f8aea76-1224-1339[2802]","name":"Virtual Class - ADMC1 and ADMC01 - Mehedi (ADMC_2)","users":{"3211-1":{"userKey":"3211-1","extId":"3211","intIds":{"w_wralypi3diyx":{"intId":"w_wralypi3diyx","registeredOn":1665959791884,"leftOn":1665959952093,"userLeftFlag":true}},"name":"Puunnapha METHEECHANGIT","isModerator":false,"isDialIn":false,"answers":{},"talk":{"totalTime":0,"lastTalkStartedOn":0},"emojis":[],"webcams":[],"totalOfMessages":1}},"polls":{},"screenshares":[],"presentationSlides":[{"presentationId":"9e0558a8298fc4f95cbea0a9a2bc391cac214867-1665959787070","pageNum":1,"setOn":1665959792683}],"createdOn":1665959787073,"endedOn":1665960022093}