{"intId":"e57e2ae367f89592c3466a41cbe595fd9e3bb4da-1670363691400","extId":"9d47e837de8b3e35b65510d647cf672eeb563138-1037-1121","name":"Virtual Class_CIIS_FSKRDG10_Calvin Zhan","users":{"3765-1":{"userKey":"3765-1","extId":"3765","intIds":{"w_cwgn3xdphs89":{"intId":"w_cwgn3xdphs89","registeredOn":1670363693934,"leftOn":1670394388867,"userLeftFlag":false}},"name":"Pei-Hung CHENG","isModerator":false,"isDialIn":false,"answers":{},"talk":{"totalTime":0,"lastTalkStartedOn":0},"emojis":[],"webcams":[],"totalOfMessages":0},"2720-1":{"userKey":"2720-1","extId":"2720","intIds":{"w_hlg3kketroc1":{"intId":"w_hlg3kketroc1","registeredOn":1670366932900,"leftOn":1670394388867,"userLeftFlag":false}},"name":"Calvin Zhan","isModerator":true,"isDialIn":false,"answers":{},"talk":{"totalTime":0,"lastTalkStartedOn":0},"emojis":[],"webcams":[],"totalOfMessages":0}},"polls":{},"screenshares":[],"presentationSlides":[{"presentationId":"19f14809e599f2f622f1c2089fbbf59c3de614dc-1670363691403","pageNum":1,"setOn":1670363697302}],"createdOn":1670363691413,"endedOn":1670394388867}