{"intId":"b7a0e3e58ca3369ba0e1fd8c7663a186a9bda8d8-1666129040254","extId":"c1f6b7c5248384b34c5af3aff560371d69864670-1208-1335[2754]","name":"Virtual Class Link for both Group CIVLM_1 and CIVLM_01 - Sazib (...","users":{"3885-1":{"userKey":"3885-1","extId":"3885","intIds":{"w_gyo25dknnmqx":{"intId":"w_gyo25dknnmqx","registeredOn":1666129047306,"leftOn":1666129075272,"userLeftFlag":true}},"name":"Yi-Tzu HSU","isModerator":false,"isDialIn":false,"answers":{},"talk":{"totalTime":0,"lastTalkStartedOn":0},"emojis":[],"webcams":[],"totalOfMessages":0}},"polls":{},"screenshares":[],"presentationSlides":[{"presentationId":"a272d7193c9e8ab32047a31085d0176e61f37890-1666129040257","pageNum":1,"setOn":1666129045873}],"createdOn":1666129040259,"endedOn":1666129145272}