{"intId":"94dd372abefb7487d6e9a8bc3b29bc6beda11c6a-1668759096413","extId":"45da03081a875d88dbf34f9d890d50e9c4ff5192-995-1106[2130]","name":"Virtual Class – Parveen (A-Online Virtual Class)","users":{"3271-1":{"userKey":"3271-1","extId":"3271","intIds":{"w_xwz3acyf1pbe":{"intId":"w_xwz3acyf1pbe","registeredOn":1668759099909,"leftOn":1668759121442,"userLeftFlag":true}},"name":"Can Mustafa KAYA","isModerator":false,"isDialIn":false,"answers":{},"talk":{"totalTime":0,"lastTalkStartedOn":0},"emojis":[],"webcams":[],"totalOfMessages":0}},"polls":{},"screenshares":[],"presentationSlides":[{"presentationId":"5825a0a5b978f0528facccb5d37f139296cc9fcb-1668759096415","pageNum":1,"setOn":1668759102327}],"createdOn":1668759096426,"endedOn":1668759181443}