{"intId":"ae2c6db1dab5e709d91bc562c816956c30d4ce88-1669405392804","extId":"7628cdf5157291bc5073ae63b5ea35afbca3a437-1216-1361[2778]","name":"Combined DLM_1 and DLM_01 Online Virtual Class - Erwan TJAN (A-O...","users":{"3668-1":{"userKey":"3668-1","extId":"3668","intIds":{"w_apwkkwavuoze":{"intId":"w_apwkkwavuoze","registeredOn":1669413186556,"leftOn":1669431277822,"userLeftFlag":true},"w_zuwadqx4xfbp":{"intId":"w_zuwadqx4xfbp","registeredOn":1669431268619,"leftOn":1669431837822,"userLeftFlag":true},"w_p7nxd7u4e1aq":{"intId":"w_p7nxd7u4e1aq","registeredOn":1669432363299,"leftOn":1669439537822,"userLeftFlag":true}},"name":"Rujaroj TECHAKAJORNKIAT","isModerator":false,"isDialIn":false,"answers":{},"talk":{"totalTime":0,"lastTalkStartedOn":0},"emojis":[],"webcams":[],"totalOfMessages":7},"3869-2":{"userKey":"3869-2","extId":"3869","intIds":{"w_juiydyadvyhy":{"intId":"w_juiydyadvyhy","registeredOn":1669428101439,"leftOn":1669439743130,"userLeftFlag":false}},"name":"Suhua QIU","isModerator":false,"isDialIn":false,"answers":{},"talk":{"totalTime":0,"lastTalkStartedOn":0},"emojis":[],"webcams":[],"totalOfMessages":2},"3504-2":{"userKey":"3504-2","extId":"3504","intIds":{"w_91n2wgluwicg":{"intId":"w_91n2wgluwicg","registeredOn":1669416117517,"leftOn":1669416167822,"userLeftFlag":true},"w_f99mplbga6eu":{"intId":"w_f99mplbga6eu","registeredOn":1669419143499,"leftOn":1669419157822,"userLeftFlag":true},"w_ewkkumbbe6wo":{"intId":"w_ewkkumbbe6wo","registeredOn":1669419659985,"leftOn":1669437147822,"userLeftFlag":true},"w_vzdk4pgminhn":{"intId":"w_vzdk4pgminhn","registeredOn":1669439659817,"leftOn":1669439743130,"userLeftFlag":true}},"name":"Yen-Xi LIN","isModerator":false,"isDialIn":false,"answers":{},"talk":{"totalTime":0,"lastTalkStartedOn":0},"emojis":[],"webcams":[],"totalOfMessages":6},"954-1":{"userKey":"954-1","extId":"954","intIds":{"w_8ii2kqhxrkeq":{"intId":"w_8ii2kqhxrkeq","registeredOn":1669413771078,"leftOn":1669439743130,"userLeftFlag":false}},"name":"Kanokphon FAENGARWUT","isModerator":false,"isDialIn":false,"answers":{},"talk":{"totalTime":0,"lastTalkStartedOn":0},"emojis":[],"webcams":[],"totalOfMessages":7},"3869-1":{"userKey":"3869-1","extId":"3869","intIds":{"w_4ilcoaa2rtad":{"intId":"w_4ilcoaa2rtad","registeredOn":1669419925017,"leftOn":1669426947822,"userLeftFlag":true},"w_nahywpcs8csy":{"intId":"w_nahywpcs8csy","registeredOn":1669426934752,"leftOn":1669433427822,"userLeftFlag":true},"w_nttaqhnbubnp":{"intId":"w_nttaqhnbubnp","registeredOn":1669415942022,"leftOn":1669417357823,"userLeftFlag":true},"w_2ffui1dq9ucb":{"intId":"w_2ffui1dq9ucb","registeredOn":1669419573289,"leftOn":1669419897822,"userLeftFlag":true},"w_ayhxu0yvgm7o":{"intId":"w_ayhxu0yvgm7o","registeredOn":1669412486661,"leftOn":1669415787823,"userLeftFlag":true}},"name":"Suhua QIU","isModerator":false,"isDialIn":false,"answers":{},"talk":{"totalTime":0,"lastTalkStartedOn":0},"emojis":[],"webcams":[],"totalOfMessages":4},"3406-1":{"userKey":"3406-1","extId":"3406","intIds":{"w_ssnm6gnvjjbr":{"intId":"w_ssnm6gnvjjbr","registeredOn":1669432568440,"leftOn":1669432937822,"userLeftFlag":true},"w_fewfwrcleor8":{"intId":"w_fewfwrcleor8","registeredOn":1669432928263,"leftOn":1669432977823,"userLeftFlag":true}},"name":"Nisachon YOOKONG","isModerator":false,"isDialIn":false,"answers":{},"talk":{"totalTime":0,"lastTalkStartedOn":0},"emojis":[],"webcams":[],"totalOfMessages":1},"3875-1":{"userKey":"3875-1","extId":"3875","intIds":{"w_nvycnalxvewi":{"intId":"w_nvycnalxvewi","registeredOn":1669429473903,"leftOn":1669430407822,"userLeftFlag":true}},"name":"Xiaodong YUAN","isModerator":false,"isDialIn":false,"answers":{},"talk":{"totalTime":0,"lastTalkStartedOn":0},"emojis":[],"webcams":[],"totalOfMessages":1},"3805-1":{"userKey":"3805-1","extId":"3805","intIds":{"w_uodbtulra5ms":{"intId":"w_uodbtulra5ms","registeredOn":1669416121259,"leftOn":1669439743130,"userLeftFlag":false}},"name":"Shu LI","isModerator":false,"isDialIn":false,"answers":{},"talk":{"totalTime":0,"lastTalkStartedOn":0},"emojis":[],"webcams":[],"totalOfMessages":1},"3435-1":{"userKey":"3435-1","extId":"3435","intIds":{"w_0evw0jzuk61g":{"intId":"w_0evw0jzuk61g","registeredOn":1669405397959,"leftOn":1669439743130,"userLeftFlag":false}},"name":"Tao LIN","isModerator":false,"isDialIn":false,"answers":{},"talk":{"totalTime":0,"lastTalkStartedOn":0},"emojis":[],"webcams":[],"totalOfMessages":1},"3504-1":{"userKey":"3504-1","extId":"3504","intIds":{"w_f99mplbga6eu":{"intId":"w_f99mplbga6eu","registeredOn":1669409698044,"leftOn":1669417237823,"userLeftFlag":true}},"name":"Yen-Xi LIN","isModerator":false,"isDialIn":false,"answers":{},"talk":{"totalTime":0,"lastTalkStartedOn":0},"emojis":[],"webcams":[],"totalOfMessages":2},"3439-1":{"userKey":"3439-1","extId":"3439","intIds":{"w_qffoftymychc":{"intId":"w_qffoftymychc","registeredOn":1669430850383,"leftOn":1669431947822,"userLeftFlag":true}},"name":"Xiao HAN","isModerator":false,"isDialIn":false,"answers":{},"talk":{"totalTime":0,"lastTalkStartedOn":0},"emojis":[{"name":"raiseHand","sentOn":1669430865990}],"webcams":[],"totalOfMessages":0},"3794-1":{"userKey":"3794-1","extId":"3794","intIds":{"w_wvoswlal1pk6":{"intId":"w_wvoswlal1pk6","registeredOn":1669415313652,"leftOn":1669416337822,"userLeftFlag":true},"w_lht2vcfswcuh":{"intId":"w_lht2vcfswcuh","registeredOn":1669426695968,"leftOn":1669426817823,"userLeftFlag":true},"w_2kzgaaimnofe":{"intId":"w_2kzgaaimnofe","registeredOn":1669438470650,"leftOn":1669438937822,"userLeftFlag":true},"w_iu1pvtmcep3e":{"intId":"w_iu1pvtmcep3e","registeredOn":1669419655706,"leftOn":1669419937823,"userLeftFlag":true},"w_brqukfptgl6b":{"intId":"w_brqukfptgl6b","registeredOn":1669423118807,"leftOn":1669423267822,"userLeftFlag":true},"w_5qbsubxnaxkm":{"intId":"w_5qbsubxnaxkm","registeredOn":1669438930924,"leftOn":1669439743130,"userLeftFlag":true},"w_0pfyypaz4pxm":{"intId":"w_0pfyypaz4pxm","registeredOn":1669435686721,"leftOn":1669438297823,"userLeftFlag":true},"w_okl5ezarqczo":{"intId":"w_okl5ezarqczo","registeredOn":1669435586287,"leftOn":1669435697823,"userLeftFlag":true},"w_9pn5u5vs6mcm":{"intId":"w_9pn5u5vs6mcm","registeredOn":1669428723534,"leftOn":1669429087812,"userLeftFlag":true},"w_61x1mwenxpdj":{"intId":"w_61x1mwenxpdj","registeredOn":1669414808052,"leftOn":1669415327822,"userLeftFlag":true}},"name":"Chia-Ying LIN","isModerator":false,"isDialIn":false,"answers":{},"talk":{"totalTime":0,"lastTalkStartedOn":0},"emojis":[],"webcams":[],"totalOfMessages":7},"3529-1":{"userKey":"3529-1","extId":"3529","intIds":{"w_wzlfsierah4g":{"intId":"w_wzlfsierah4g","registeredOn":1669418387149,"leftOn":1669420067822,"userLeftFlag":true},"w_sr6g0yva87fv":{"intId":"w_sr6g0yva87fv","registeredOn":1669434587205,"leftOn":1669437777822,"userLeftFlag":true},"w_lwcj6yd9trji":{"intId":"w_lwcj6yd9trji","registeredOn":1669421208791,"leftOn":1669428857822,"userLeftFlag":true},"w_scgizhpukoyr":{"intId":"w_scgizhpukoyr","registeredOn":1669420319753,"leftOn":1669420537822,"userLeftFlag":true},"w_6a01umbyp5yc":{"intId":"w_6a01umbyp5yc","registeredOn":1669431643692,"leftOn":1669434597822,"userLeftFlag":true},"w_d6vavdawfobh":{"intId":"w_d6vavdawfobh","registeredOn":1669428851544,"leftOn":1669431657822,"userLeftFlag":true},"w_gs3zlviejlpz":{"intId":"w_gs3zlviejlpz","registeredOn":1669437770455,"leftOn":1669439743130,"userLeftFlag":true},"w_btj2clzgbx4t":{"intId":"w_btj2clzgbx4t","registeredOn":1669420593425,"leftOn":1669421217822,"userLeftFlag":true}},"name":"Jaeseung LEE","isModerator":false,"isDialIn":false,"answers":{},"talk":{"totalTime":0,"lastTalkStartedOn":0},"emojis":[],"webcams":[],"totalOfMessages":3},"3726-1":{"userKey":"3726-1","extId":"3726","intIds":{"w_erkio9eepkcd":{"intId":"w_erkio9eepkcd","registeredOn":1669423576947,"leftOn":1669423647822,"userLeftFlag":true},"w_cjkr0xr8ptzy":{"intId":"w_cjkr0xr8ptzy","registeredOn":1669425035749,"leftOn":1669439743130,"userLeftFlag":false}},"name":"Ya-Hsuan LIN","isModerator":false,"isDialIn":false,"answers":{},"talk":{"totalTime":0,"lastTalkStartedOn":0},"emojis":[],"webcams":[],"totalOfMessages":5},"3549-1":{"userKey":"3549-1","extId":"3549","intIds":{"w_9tp1flo4rvii":{"intId":"w_9tp1flo4rvii","registeredOn":1669413553501,"leftOn":1669420487822,"userLeftFlag":true},"w_x0wxgzaim33e":{"intId":"w_x0wxgzaim33e","registeredOn":1669420602145,"leftOn":1669439743130,"userLeftFlag":false}},"name":"Wanxuan ZHANG","isModerator":false,"isDialIn":false,"answers":{},"talk":{"totalTime":0,"lastTalkStartedOn":0},"emojis":[],"webcams":[],"totalOfMessages":7},"3728-1":{"userKey":"3728-1","extId":"3728","intIds":{"w_s8zdalnfzn8t":{"intId":"w_s8zdalnfzn8t","registeredOn":1669416465504,"leftOn":1669436967822,"userLeftFlag":true},"w_9f5zrjh0zx5m":{"intId":"w_9f5zrjh0zx5m","registeredOn":1669437005333,"leftOn":1669437097822,"userLeftFlag":true}},"name":"Thi My Hoa TRINH","isModerator":false,"isDialIn":false,"answers":{},"talk":{"totalTime":0,"lastTalkStartedOn":0},"emojis":[],"webcams":[],"totalOfMessages":2},"10-1":{"userKey":"10-1","extId":"10","intIds":{"w_wdqfxlsf2ojh":{"intId":"w_wdqfxlsf2ojh","registeredOn":1669425668449,"leftOn":1669425947822,"userLeftFlag":true},"w_jrd5fwgdtiw9":{"intId":"w_jrd5fwgdtiw9","registeredOn":1669411956651,"leftOn":1669425637822,"userLeftFlag":true},"w_mnqnnqlkvoa9":{"intId":"w_mnqnnqlkvoa9","registeredOn":1669425960715,"leftOn":1669429607822,"userLeftFlag":true},"w_qnlumnmsbcvi":{"intId":"w_qnlumnmsbcvi","registeredOn":1669434901376,"leftOn":1669438907822,"userLeftFlag":true},"w_d8hdtvpiluqo":{"intId":"w_d8hdtvpiluqo","registeredOn":1669438907451,"leftOn":1669439743130,"userLeftFlag":false},"w_hwc9bbzcyg8i":{"intId":"w_hwc9bbzcyg8i","registeredOn":1669430105264,"leftOn":1669434907822,"userLeftFlag":true}},"name":"Erwan Tjan","isModerator":true,"isDialIn":false,"answers":{},"talk":{"totalTime":86339,"lastTalkStartedOn":0},"emojis":[],"webcams":[],"totalOfMessages":48},"3775-1":{"userKey":"3775-1","extId":"3775","intIds":{"w_m7ophrxwnmqu":{"intId":"w_m7ophrxwnmqu","registeredOn":1669432518697,"leftOn":1669432577822,"userLeftFlag":true},"w_4qiulrsvchvw":{"intId":"w_4qiulrsvchvw","registeredOn":1669435816225,"leftOn":1669435877822,"userLeftFlag":true},"w_0onmkg5sjoqo":{"intId":"w_0onmkg5sjoqo","registeredOn":1669428924226,"leftOn":1669428987822,"userLeftFlag":true},"w_olcpygclov8u":{"intId":"w_olcpygclov8u","registeredOn":1669419930775,"leftOn":1669420127822,"userLeftFlag":true},"w_4o6b9gemrm7r":{"intId":"w_4o6b9gemrm7r","registeredOn":1669423561415,"leftOn":1669423667822,"userLeftFlag":true},"w_khzulrzgd1th":{"intId":"w_khzulrzgd1th","registeredOn":1669416397115,"leftOn":1669419937823,"userLeftFlag":true},"w_ztalyqp1i4we":{"intId":"w_ztalyqp1i4we","registeredOn":1669426815627,"leftOn":1669428937823,"userLeftFlag":true}},"name":"Le Mai Han TRAN","isModerator":false,"isDialIn":false,"answers":{},"talk":{"totalTime":0,"lastTalkStartedOn":0},"emojis":[],"webcams":[],"totalOfMessages":7},"3431-1":{"userKey":"3431-1","extId":"3431","intIds":{"w_okapccenpli6":{"intId":"w_okapccenpli6","registeredOn":1669413341031,"leftOn":1669439743130,"userLeftFlag":false}},"name":"Quang Trung NGUYEN","isModerator":false,"isDialIn":false,"answers":{},"talk":{"totalTime":0,"lastTalkStartedOn":0},"emojis":[],"webcams":[],"totalOfMessages":3},"3581-1":{"userKey":"3581-1","extId":"3581","intIds":{"w_gvmyylywqypp":{"intId":"w_gvmyylywqypp","registeredOn":1669415227838,"leftOn":1669419957822,"userLeftFlag":true},"w_ragacl2kfxk6":{"intId":"w_ragacl2kfxk6","registeredOn":1669419946411,"leftOn":1669439743130,"userLeftFlag":false}},"name":"Thi Hong Loan PHAN","isModerator":false,"isDialIn":false,"answers":{},"talk":{"totalTime":0,"lastTalkStartedOn":0},"emojis":[],"webcams":[],"totalOfMessages":4}},"polls":{},"screenshares":[],"presentationSlides":[{"presentationId":"2a2d8b21529779f12abd7b5caacc26c33d064b7e-1669405392805","pageNum":1,"setOn":1669405398917},{"presentationId":"77c6d3aa98efa52eb732d065ef836b084e871f3d-1669412018171","pageNum":1,"setOn":1669412024223},{"presentationId":"77c6d3aa98efa52eb732d065ef836b084e871f3d-1669412018171","pageNum":2,"setOn":1669412028426},{"presentationId":"77c6d3aa98efa52eb732d065ef836b084e871f3d-1669412018171","pageNum":3,"setOn":1669412029278},{"presentationId":"77c6d3aa98efa52eb732d065ef836b084e871f3d-1669412018171","pageNum":4,"setOn":1669412030161},{"presentationId":"77c6d3aa98efa52eb732d065ef836b084e871f3d-1669412018171","pageNum":5,"setOn":1669412031101},{"presentationId":"c0c58308d951a25c1010fc35f15cee29a01a406a-1669413942430","pageNum":1,"setOn":1669413949968},{"presentationId":"c0c58308d951a25c1010fc35f15cee29a01a406a-1669413942430","pageNum":10,"setOn":1669413955313},{"presentationId":"c0c58308d951a25c1010fc35f15cee29a01a406a-1669413942430","pageNum":11,"setOn":1669413958160},{"presentationId":"c0c58308d951a25c1010fc35f15cee29a01a406a-1669413942430","pageNum":12,"setOn":1669413958605},{"presentationId":"c0c58308d951a25c1010fc35f15cee29a01a406a-1669413942430","pageNum":13,"setOn":1669413959079},{"presentationId":"c0c58308d951a25c1010fc35f15cee29a01a406a-1669413942430","pageNum":14,"setOn":1669413959954},{"presentationId":"c0c58308d951a25c1010fc35f15cee29a01a406a-1669413942430","pageNum":15,"setOn":1669413960532},{"presentationId":"c0c58308d951a25c1010fc35f15cee29a01a406a-1669413942430","pageNum":16,"setOn":1669413961400},{"presentationId":"c0c58308d951a25c1010fc35f15cee29a01a406a-1669413942430","pageNum":17,"setOn":1669413962225},{"presentationId":"c0c58308d951a25c1010fc35f15cee29a01a406a-1669413942430","pageNum":18,"setOn":1669413964145},{"presentationId":"c0c58308d951a25c1010fc35f15cee29a01a406a-1669413942430","pageNum":19,"setOn":1669416343853},{"presentationId":"c0c58308d951a25c1010fc35f15cee29a01a406a-1669413942430","pageNum":20,"setOn":1669419771589},{"presentationId":"c0c58308d951a25c1010fc35f15cee29a01a406a-1669413942430","pageNum":21,"setOn":1669419773267},{"presentationId":"c0c58308d951a25c1010fc35f15cee29a01a406a-1669413942430","pageNum":22,"setOn":1669423043330},{"presentationId":"c0c58308d951a25c1010fc35f15cee29a01a406a-1669413942430","pageNum":23,"setOn":1669423044732},{"presentationId":"c0c58308d951a25c1010fc35f15cee29a01a406a-1669413942430","pageNum":24,"setOn":1669423046900},{"presentationId":"c0c58308d951a25c1010fc35f15cee29a01a406a-1669413942430","pageNum":25,"setOn":1669423218936},{"presentationId":"c0c58308d951a25c1010fc35f15cee29a01a406a-1669413942430","pageNum":26,"setOn":1669426240534},{"presentationId":"c0c58308d951a25c1010fc35f15cee29a01a406a-1669413942430","pageNum":25,"setOn":1669426243212},{"presentationId":"c0c58308d951a25c1010fc35f15cee29a01a406a-1669413942430","pageNum":26,"setOn":1669426337657},{"presentationId":"c0c58308d951a25c1010fc35f15cee29a01a406a-1669413942430","pageNum":27,"setOn":1669426339081},{"presentationId":"c0c58308d951a25c1010fc35f15cee29a01a406a-1669413942430","pageNum":28,"setOn":1669426341211},{"presentationId":"c0c58308d951a25c1010fc35f15cee29a01a406a-1669413942430","pageNum":29,"setOn":1669426342097},{"presentationId":"c0c58308d951a25c1010fc35f15cee29a01a406a-1669413942430","pageNum":28,"setOn":1669426342972},{"presentationId":"c0c58308d951a25c1010fc35f15cee29a01a406a-1669413942430","pageNum":27,"setOn":1669426343965},{"presentationId":"c0c58308d951a25c1010fc35f15cee29a01a406a-1669413942430","pageNum":26,"setOn":1669426351849},{"presentationId":"c0c58308d951a25c1010fc35f15cee29a01a406a-1669413942430","pageNum":27,"setOn":1669430129135},{"presentationId":"c0c58308d951a25c1010fc35f15cee29a01a406a-1669413942430","pageNum":28,"setOn":1669432381508},{"presentationId":"c0c58308d951a25c1010fc35f15cee29a01a406a-1669413942430","pageNum":27,"setOn":1669432384180},{"presentationId":"c0c58308d951a25c1010fc35f15cee29a01a406a-1669413942430","pageNum":26,"setOn":1669432386127},{"presentationId":"c0c58308d951a25c1010fc35f15cee29a01a406a-1669413942430","pageNum":25,"setOn":1669432387107},{"presentationId":"c0c58308d951a25c1010fc35f15cee29a01a406a-1669413942430","pageNum":26,"setOn":1669432388656},{"presentationId":"c0c58308d951a25c1010fc35f15cee29a01a406a-1669413942430","pageNum":27,"setOn":1669432389284},{"presentationId":"c0c58308d951a25c1010fc35f15cee29a01a406a-1669413942430","pageNum":28,"setOn":1669432389955},{"presentationId":"c0c58308d951a25c1010fc35f15cee29a01a406a-1669413942430","pageNum":29,"setOn":1669432390689},{"presentationId":"c0c58308d951a25c1010fc35f15cee29a01a406a-1669413942430","pageNum":30,"setOn":1669432393890},{"presentationId":"c0c58308d951a25c1010fc35f15cee29a01a406a-1669413942430","pageNum":31,"setOn":1669432431473},{"presentationId":"c0c58308d951a25c1010fc35f15cee29a01a406a-1669413942430","pageNum":32,"setOn":1669432432157},{"presentationId":"c0c58308d951a25c1010fc35f15cee29a01a406a-1669413942430","pageNum":33,"setOn":1669432432706},{"presentationId":"c0c58308d951a25c1010fc35f15cee29a01a406a-1669413942430","pageNum":32,"setOn":1669432433525},{"presentationId":"c0c58308d951a25c1010fc35f15cee29a01a406a-1669413942430","pageNum":31,"setOn":1669432433746},{"presentationId":"c0c58308d951a25c1010fc35f15cee29a01a406a-1669413942430","pageNum":30,"setOn":1669432434080},{"presentationId":"c0c58308d951a25c1010fc35f15cee29a01a406a-1669413942430","pageNum":31,"setOn":1669432436350},{"presentationId":"c0c58308d951a25c1010fc35f15cee29a01a406a-1669413942430","pageNum":30,"setOn":1669432437929},{"presentationId":"c0c58308d951a25c1010fc35f15cee29a01a406a-1669413942430","pageNum":31,"setOn":1669435976137},{"presentationId":"c0c58308d951a25c1010fc35f15cee29a01a406a-1669413942430","pageNum":32,"setOn":1669435997928},{"presentationId":"c0c58308d951a25c1010fc35f15cee29a01a406a-1669413942430","pageNum":31,"setOn":1669435998533},{"presentationId":"7c0dc89e6f31ed8c008c1a5e6d4ba72089b3c8c5-1669436247429","pageNum":1,"setOn":1669436257970},{"presentationId":"7c0dc89e6f31ed8c008c1a5e6d4ba72089b3c8c5-1669436247429","pageNum":67,"setOn":1669438916179},{"presentationId":"7c0dc89e6f31ed8c008c1a5e6d4ba72089b3c8c5-1669436247429","pageNum":66,"setOn":1669438919086},{"presentationId":"7c0dc89e6f31ed8c008c1a5e6d4ba72089b3c8c5-1669436247429","pageNum":23,"setOn":1669438922428},{"presentationId":"c0c58308d951a25c1010fc35f15cee29a01a406a-1669413942430","pageNum":31,"setOn":1669438928093},{"presentationId":"c0c58308d951a25c1010fc35f15cee29a01a406a-1669413942430","pageNum":32,"setOn":1669438929354},{"presentationId":"7c0dc89e6f31ed8c008c1a5e6d4ba72089b3c8c5-1669436247429","pageNum":23,"setOn":1669438939174},{"presentationId":"7c0dc89e6f31ed8c008c1a5e6d4ba72089b3c8c5-1669436247429","pageNum":24,"setOn":1669438941630},{"presentationId":"7c0dc89e6f31ed8c008c1a5e6d4ba72089b3c8c5-1669436247429","pageNum":25,"setOn":1669438942146},{"presentationId":"7c0dc89e6f31ed8c008c1a5e6d4ba72089b3c8c5-1669436247429","pageNum":26,"setOn":1669438942829},{"presentationId":"7c0dc89e6f31ed8c008c1a5e6d4ba72089b3c8c5-1669436247429","pageNum":27,"setOn":1669438943600},{"presentationId":"7c0dc89e6f31ed8c008c1a5e6d4ba72089b3c8c5-1669436247429","pageNum":28,"setOn":1669438944601},{"presentationId":"7c0dc89e6f31ed8c008c1a5e6d4ba72089b3c8c5-1669436247429","pageNum":29,"setOn":1669438949139},{"presentationId":"7c0dc89e6f31ed8c008c1a5e6d4ba72089b3c8c5-1669436247429","pageNum":30,"setOn":1669438950095},{"presentationId":"7c0dc89e6f31ed8c008c1a5e6d4ba72089b3c8c5-1669436247429","pageNum":31,"setOn":1669438951077},{"presentationId":"7c0dc89e6f31ed8c008c1a5e6d4ba72089b3c8c5-1669436247429","pageNum":32,"setOn":1669438952011},{"presentationId":"7c0dc89e6f31ed8c008c1a5e6d4ba72089b3c8c5-1669436247429","pageNum":33,"setOn":1669438954069},{"presentationId":"7c0dc89e6f31ed8c008c1a5e6d4ba72089b3c8c5-1669436247429","pageNum":34,"setOn":1669438956272},{"presentationId":"7c0dc89e6f31ed8c008c1a5e6d4ba72089b3c8c5-1669436247429","pageNum":33,"setOn":1669438957144},{"presentationId":"7c0dc89e6f31ed8c008c1a5e6d4ba72089b3c8c5-1669436247429","pageNum":32,"setOn":1669438958812},{"presentationId":"77c6d3aa98efa52eb732d065ef836b084e871f3d-1669412018171","pageNum":5,"setOn":1669439625359},{"presentationId":"77c6d3aa98efa52eb732d065ef836b084e871f3d-1669412018171","pageNum":9,"setOn":1669439627574}],"createdOn":1669405392805,"endedOn":1669439743130}