{"intId":"f3908d2e8bdefc2313ddc01557f6c42ca25e8d25-1666676602945","extId":"64fc7af3952920317438aaa8dc032a9854aaf12a-1196-1310[2716]","name":"ADMC_2 @Ahasan (ADMC_2)","users":{"3588-1":{"userKey":"3588-1","extId":"3588","intIds":{"w_8ulcqccwib7m":{"intId":"w_8ulcqccwib7m","registeredOn":1666676604753,"leftOn":1666695147962,"userLeftFlag":true}},"name":"Thanatcha Budda","isModerator":false,"isDialIn":false,"answers":{},"talk":{"totalTime":0,"lastTalkStartedOn":0},"emojis":[],"webcams":[],"totalOfMessages":0},"3588-2":{"userKey":"3588-2","extId":"3588","intIds":{"w_2vfcru7jbemz":{"intId":"w_2vfcru7jbemz","registeredOn":1666676672456,"leftOn":1666695147962,"userLeftFlag":true}},"name":"Thanatcha Budda","isModerator":false,"isDialIn":false,"answers":{},"talk":{"totalTime":0,"lastTalkStartedOn":0},"emojis":[],"webcams":[],"totalOfMessages":0}},"polls":{},"screenshares":[],"presentationSlides":[{"presentationId":"8600aadafd1c9d99c94736d80983938c18a81e44-1666676602947","pageNum":1,"setOn":1666676608296}],"createdOn":1666676602949,"endedOn":1666695217963}