{"intId":"e6ab09bbbe2bef26f90028dc6441c6103dca7721-1668202458877","extId":"9e2d771109065ccd02b11918962d6e2c97f0d754-1215-1349[2775]","name":"Combined DLM_1 and DLM_01 Online Virtual Class - Erwan TJAN (A-O...","users":{"3668-1":{"userKey":"3668-1","extId":"3668","intIds":{"w_3jzdeflo4duu":{"intId":"w_3jzdeflo4duu","registeredOn":1668206774596,"leftOn":1668226913892,"userLeftFlag":true}},"name":"Rujaroj TECHAKAJORNKIAT","isModerator":false,"isDialIn":false,"answers":{},"talk":{"totalTime":0,"lastTalkStartedOn":0},"emojis":[],"webcams":[],"totalOfMessages":5},"3504-2":{"userKey":"3504-2","extId":"3504","intIds":{"w_zgjgxpgxbdhz":{"intId":"w_zgjgxpgxbdhz","registeredOn":1668219533534,"leftOn":1668220213893,"userLeftFlag":true},"w_adqeonofdu7r":{"intId":"w_adqeonofdu7r","registeredOn":1668213686483,"leftOn":1668214783892,"userLeftFlag":true},"w_rugmzgis0dfk":{"intId":"w_rugmzgis0dfk","registeredOn":1668216966899,"leftOn":1668218323892,"userLeftFlag":true},"w_cgsqssmdpgzd":{"intId":"w_cgsqssmdpgzd","registeredOn":1668222902810,"leftOn":1668223633892,"userLeftFlag":true},"w_qat9mqixnbtt":{"intId":"w_qat9mqixnbtt","registeredOn":1668206581928,"leftOn":1668208173893,"userLeftFlag":true},"w_9c3rhvq413mi":{"intId":"w_9c3rhvq413mi","registeredOn":1668215701745,"leftOn":1668216383892,"userLeftFlag":true}},"name":"Yen-Xi LIN","isModerator":false,"isDialIn":false,"answers":{},"talk":{"totalTime":0,"lastTalkStartedOn":0},"emojis":[],"webcams":[],"totalOfMessages":3},"954-1":{"userKey":"954-1","extId":"954","intIds":{"w_mgrld35g4irz":{"intId":"w_mgrld35g4irz","registeredOn":1668219756891,"leftOn":1668222793892,"userLeftFlag":true},"w_uivh8eac7isj":{"intId":"w_uivh8eac7isj","registeredOn":1668204163447,"leftOn":1668206503892,"userLeftFlag":true},"w_cizmolkwpcia":{"intId":"w_cizmolkwpcia","registeredOn":1668223746020,"leftOn":1668223953882,"userLeftFlag":true},"w_3sbbuegzvy4y":{"intId":"w_3sbbuegzvy4y","registeredOn":1668217219009,"leftOn":1668217953893,"userLeftFlag":true},"w_m7bsplrhve87":{"intId":"w_m7bsplrhve87","registeredOn":1668210093458,"leftOn":1668210263893,"userLeftFlag":true},"w_ro29qdhaw4pa":{"intId":"w_ro29qdhaw4pa","registeredOn":1668226388412,"leftOn":1668226603892,"userLeftFlag":true},"w_igaruxppnyh1":{"intId":"w_igaruxppnyh1","registeredOn":1668226340726,"leftOn":1668226403893,"userLeftFlag":true},"w_xkgv75kw9ce7":{"intId":"w_xkgv75kw9ce7","registeredOn":1668206495685,"leftOn":1668210103893,"userLeftFlag":true},"w_lnkm5fpejrtn":{"intId":"w_lnkm5fpejrtn","registeredOn":1668229925012,"leftOn":1668230183893,"userLeftFlag":true},"w_wthgfeh1ot85":{"intId":"w_wthgfeh1ot85","registeredOn":1668222783366,"leftOn":1668223653892,"userLeftFlag":true},"w_kynpx0ypsgxz":{"intId":"w_kynpx0ypsgxz","registeredOn":1668213746830,"leftOn":1668214473893,"userLeftFlag":true},"w_njhvs3vxcjsx":{"intId":"w_njhvs3vxcjsx","registeredOn":1668228823842,"leftOn":1668229933892,"userLeftFlag":true}},"name":"Kanokphon FAENGARWUT","isModerator":false,"isDialIn":false,"answers":{},"talk":{"totalTime":0,"lastTalkStartedOn":0},"emojis":[],"webcams":[],"totalOfMessages":8},"3875-1":{"userKey":"3875-1","extId":"3875","intIds":{"w_cekuxdy6czxn":{"intId":"w_cekuxdy6czxn","registeredOn":1668226533826,"leftOn":1668226583892,"userLeftFlag":true},"w_oe0itfyu1vni":{"intId":"w_oe0itfyu1vni","registeredOn":1668230125288,"leftOn":1668230163893,"userLeftFlag":true},"w_prmvlpbwtbai":{"intId":"w_prmvlpbwtbai","registeredOn":1668202808850,"leftOn":1668210363893,"userLeftFlag":true},"w_3rv9rejvvmzt":{"intId":"w_3rv9rejvvmzt","registeredOn":1668222925192,"leftOn":1668224613893,"userLeftFlag":true},"w_x2pyt7kpao0w":{"intId":"w_x2pyt7kpao0w","registeredOn":1668217528388,"leftOn":1668218863893,"userLeftFlag":true},"w_18dtsxebdbvh":{"intId":"w_18dtsxebdbvh","registeredOn":1668202802719,"leftOn":1668202823892,"userLeftFlag":true},"w_tlehbs6a9t6h":{"intId":"w_tlehbs6a9t6h","registeredOn":1668213958040,"leftOn":1668213993892,"userLeftFlag":true}},"name":"Xiaodong YUAN","isModerator":false,"isDialIn":false,"answers":{},"talk":{"totalTime":0,"lastTalkStartedOn":0},"emojis":[],"webcams":[],"totalOfMessages":9},"3805-1":{"userKey":"3805-1","extId":"3805","intIds":{"w_y4fhu7b7saee":{"intId":"w_y4fhu7b7saee","registeredOn":1668204664191,"leftOn":1668230215073,"userLeftFlag":false}},"name":"Shu LI","isModerator":false,"isDialIn":false,"answers":{},"talk":{"totalTime":0,"lastTalkStartedOn":0},"emojis":[],"webcams":[],"totalOfMessages":1},"3435-1":{"userKey":"3435-1","extId":"3435","intIds":{"w_en8fheouq9of":{"intId":"w_en8fheouq9of","registeredOn":1668215747113,"leftOn":1668230215073,"userLeftFlag":false}},"name":"Tao LIN","isModerator":false,"isDialIn":false,"answers":{},"talk":{"totalTime":0,"lastTalkStartedOn":0},"emojis":[],"webcams":[],"totalOfMessages":1},"3529-1":{"userKey":"3529-1","extId":"3529","intIds":{"w_zyezvjhudgqr":{"intId":"w_zyezvjhudgqr","registeredOn":1668216835111,"leftOn":1668223543893,"userLeftFlag":true},"w_clswzfxm6hnr":{"intId":"w_clswzfxm6hnr","registeredOn":1668213782787,"leftOn":1668216573893,"userLeftFlag":true},"w_nrsoz8qlvlry":{"intId":"w_nrsoz8qlvlry","registeredOn":1668216564752,"leftOn":1668216843892,"userLeftFlag":true},"w_gto2cyuattbt":{"intId":"w_gto2cyuattbt","registeredOn":1668223533598,"leftOn":1668229993892,"userLeftFlag":true},"w_ap5r2c6i9khz":{"intId":"w_ap5r2c6i9khz","registeredOn":1668208988370,"leftOn":1668213193892,"userLeftFlag":true},"w_jiqlkjlpe6jm":{"intId":"w_jiqlkjlpe6jm","registeredOn":1668208525488,"leftOn":1668209003892,"userLeftFlag":true},"w_9evzplimsvcj":{"intId":"w_9evzplimsvcj","registeredOn":1668213187813,"leftOn":1668213543892,"userLeftFlag":true},"w_b6hc7l8izm43":{"intId":"w_b6hc7l8izm43","registeredOn":1668213537487,"leftOn":1668213793892,"userLeftFlag":true},"w_opvlwsncvcur":{"intId":"w_opvlwsncvcur","registeredOn":1668229984854,"leftOn":1668230163893,"userLeftFlag":true}},"name":"Jaeseung LEE","isModerator":false,"isDialIn":false,"answers":{},"talk":{"totalTime":0,"lastTalkStartedOn":0},"emojis":[],"webcams":[],"totalOfMessages":5},"3726-1":{"userKey":"3726-1","extId":"3726","intIds":{"w_kounptvt6hmj":{"intId":"w_kounptvt6hmj","registeredOn":1668208942153,"leftOn":1668209183893,"userLeftFlag":true},"w_tx867edjmu4k":{"intId":"w_tx867edjmu4k","registeredOn":1668213697825,"leftOn":1668214013892,"userLeftFlag":true},"w_vhzdol6afs2j":{"intId":"w_vhzdol6afs2j","registeredOn":1668221218367,"leftOn":1668221353893,"userLeftFlag":true},"w_gtgctmcy1pz3":{"intId":"w_gtgctmcy1pz3","registeredOn":1668223030392,"leftOn":1668223243893,"userLeftFlag":true},"w_ggxuzocvksj1":{"intId":"w_ggxuzocvksj1","registeredOn":1668210405657,"leftOn":1668210523892,"userLeftFlag":true},"w_g2hegmfcjek9":{"intId":"w_g2hegmfcjek9","registeredOn":1668226544511,"leftOn":1668226633893,"userLeftFlag":true},"w_aa4sqqbfnjcv":{"intId":"w_aa4sqqbfnjcv","registeredOn":1668229632130,"leftOn":1668230203892,"userLeftFlag":true}},"name":"Ya-Hsuan LIN","isModerator":false,"isDialIn":false,"answers":{},"talk":{"totalTime":0,"lastTalkStartedOn":0},"emojis":[],"webcams":[],"totalOfMessages":7},"3549-1":{"userKey":"3549-1","extId":"3549","intIds":{"w_v2gebvhgpw25":{"intId":"w_v2gebvhgpw25","registeredOn":1668203983319,"leftOn":1668230215073,"userLeftFlag":false}},"name":"Wanxuan ZHANG","isModerator":false,"isDialIn":false,"answers":{},"talk":{"totalTime":0,"lastTalkStartedOn":0},"emojis":[],"webcams":[],"totalOfMessages":2},"3728-1":{"userKey":"3728-1","extId":"3728","intIds":{"w_l2t9nqtemw09":{"intId":"w_l2t9nqtemw09","registeredOn":1668206810204,"leftOn":1668212153892,"userLeftFlag":true}},"name":"Thi My Hoa TRINH","isModerator":false,"isDialIn":false,"answers":{},"talk":{"totalTime":0,"lastTalkStartedOn":0},"emojis":[],"webcams":[],"totalOfMessages":1},"10-1":{"userKey":"10-1","extId":"10","intIds":{"w_srlwt7i7k4my":{"intId":"w_srlwt7i7k4my","registeredOn":1668218153737,"leftOn":1668226093892,"userLeftFlag":true},"w_kyuzhthiqxhx":{"intId":"w_kyuzhthiqxhx","registeredOn":1668228570527,"leftOn":1668230215073,"userLeftFlag":false},"w_edq858squn45":{"intId":"w_edq858squn45","registeredOn":1668226088278,"leftOn":1668228423892,"userLeftFlag":true},"w_qzlpbbzxhpts":{"intId":"w_qzlpbbzxhpts","registeredOn":1668217526069,"leftOn":1668218123892,"userLeftFlag":true},"w_bkm1260x1qqk":{"intId":"w_bkm1260x1qqk","registeredOn":1668202510794,"leftOn":1668217513893,"userLeftFlag":true}},"name":"Erwan Tjan","isModerator":true,"isDialIn":false,"answers":{},"talk":{"totalTime":55203,"lastTalkStartedOn":0},"emojis":[],"webcams":[],"totalOfMessages":31},"3533-2":{"userKey":"3533-2","extId":"3533","intIds":{"w_rsbfxjj8etws":{"intId":"w_rsbfxjj8etws","registeredOn":1668213238198,"leftOn":1668213263893,"userLeftFlag":true},"w_judepiikgyko":{"intId":"w_judepiikgyko","registeredOn":1668213803081,"leftOn":1668214023893,"userLeftFlag":true}},"name":"Diogo VALERIANO BATISTA","isModerator":false,"isDialIn":false,"answers":{},"talk":{"totalTime":0,"lastTalkStartedOn":0},"emojis":[],"webcams":[],"totalOfMessages":1},"3431-1":{"userKey":"3431-1","extId":"3431","intIds":{"w_sjnpiyeu3hmz":{"intId":"w_sjnpiyeu3hmz","registeredOn":1668206490376,"leftOn":1668230215073,"userLeftFlag":false}},"name":"Quang Trung NGUYEN","isModerator":false,"isDialIn":false,"answers":{},"talk":{"totalTime":0,"lastTalkStartedOn":0},"emojis":[],"webcams":[],"totalOfMessages":2},"3581-1":{"userKey":"3581-1","extId":"3581","intIds":{"w_tghsb1c49pq7":{"intId":"w_tghsb1c49pq7","registeredOn":1668206345699,"leftOn":1668217473893,"userLeftFlag":true},"w_fcnhliccqlad":{"intId":"w_fcnhliccqlad","registeredOn":1668217460233,"leftOn":1668230215073,"userLeftFlag":false}},"name":"Thi Hong Loan PHAN","isModerator":false,"isDialIn":false,"answers":{},"talk":{"totalTime":0,"lastTalkStartedOn":0},"emojis":[],"webcams":[],"totalOfMessages":7},"3869-1":{"userKey":"3869-1","extId":"3869","intIds":{"w_inl0vumlu85m":{"intId":"w_inl0vumlu85m","registeredOn":1668229726927,"leftOn":1668230183893,"userLeftFlag":true},"w_zwsjfslvrrdi":{"intId":"w_zwsjfslvrrdi","registeredOn":1668202548614,"leftOn":1668207443892,"userLeftFlag":true},"w_l758sw0zpggb":{"intId":"w_l758sw0zpggb","registeredOn":1668217634132,"leftOn":1668217663892,"userLeftFlag":true},"w_emmcozl49ehz":{"intId":"w_emmcozl49ehz","registeredOn":1668213085131,"leftOn":1668213483893,"userLeftFlag":true},"w_qguh2fwkyzra":{"intId":"w_qguh2fwkyzra","registeredOn":1668209935826,"leftOn":1668211623892,"userLeftFlag":true},"w_wrty2njxvdj2":{"intId":"w_wrty2njxvdj2","registeredOn":1668220955162,"leftOn":1668220993893,"userLeftFlag":true},"w_nx32gbvdcqxq":{"intId":"w_nx32gbvdcqxq","registeredOn":1668213497352,"leftOn":1668217123892,"userLeftFlag":true},"w_6yjfof9kwgmb":{"intId":"w_6yjfof9kwgmb","registeredOn":1668222842370,"leftOn":1668225803892,"userLeftFlag":true},"w_liamltwtk0if":{"intId":"w_liamltwtk0if","registeredOn":1668226386273,"leftOn":1668226893892,"userLeftFlag":true},"w_5blmmavevoim":{"intId":"w_5blmmavevoim","registeredOn":1668217191063,"leftOn":1668217643892,"userLeftFlag":true}},"name":"Suhua QIU","isModerator":false,"isDialIn":false,"answers":{},"talk":{"totalTime":0,"lastTalkStartedOn":0},"emojis":[],"webcams":[],"totalOfMessages":10},"3423-1":{"userKey":"3423-1","extId":"3423","intIds":{"w_emjbfbuscsbv":{"intId":"w_emjbfbuscsbv","registeredOn":1668207083429,"leftOn":1668207113892,"userLeftFlag":true},"w_xmkqnkorm63i":{"intId":"w_xmkqnkorm63i","registeredOn":1668207103609,"leftOn":1668224093892,"userLeftFlag":true}},"name":"Xiangdan SONG","isModerator":false,"isDialIn":false,"answers":{},"talk":{"totalTime":0,"lastTalkStartedOn":0},"emojis":[],"webcams":[],"totalOfMessages":2},"3533-1":{"userKey":"3533-1","extId":"3533","intIds":{"w_agfbiflkbwqw":{"intId":"w_agfbiflkbwqw","registeredOn":1668213147559,"leftOn":1668213303892,"userLeftFlag":true}},"name":"Diogo VALERIANO BATISTA","isModerator":false,"isDialIn":false,"answers":{},"talk":{"totalTime":0,"lastTalkStartedOn":0},"emojis":[],"webcams":[],"totalOfMessages":2},"3406-1":{"userKey":"3406-1","extId":"3406","intIds":{"w_n7vfwmgbardq":{"intId":"w_n7vfwmgbardq","registeredOn":1668218989747,"leftOn":1668219053893,"userLeftFlag":true}},"name":"Nisachon YOOKONG","isModerator":false,"isDialIn":false,"answers":{},"talk":{"totalTime":0,"lastTalkStartedOn":0},"emojis":[],"webcams":[],"totalOfMessages":1},"3896-1":{"userKey":"3896-1","extId":"3896","intIds":{"w_3edyjcb9slyp":{"intId":"w_3edyjcb9slyp","registeredOn":1668202460556,"leftOn":1668202523883,"userLeftFlag":true},"w_vburpi9ljuap":{"intId":"w_vburpi9ljuap","registeredOn":1668226472112,"leftOn":1668226763892,"userLeftFlag":true},"w_ndan2umrw4lt":{"intId":"w_ndan2umrw4lt","registeredOn":1668226748848,"leftOn":1668230215073,"userLeftFlag":false},"w_xbatghx2dxgc":{"intId":"w_xbatghx2dxgc","registeredOn":1668226421044,"leftOn":1668226483892,"userLeftFlag":true},"w_ofnfak6ksjjh":{"intId":"w_ofnfak6ksjjh","registeredOn":1668202549428,"leftOn":1668226403893,"userLeftFlag":true}},"name":"Nittaya PINTIP","isModerator":false,"isDialIn":false,"answers":{},"talk":{"totalTime":0,"lastTalkStartedOn":0},"emojis":[],"webcams":[],"totalOfMessages":8},"3504-1":{"userKey":"3504-1","extId":"3504","intIds":{"w_cx01gt15flnl":{"intId":"w_cx01gt15flnl","registeredOn":1668206336561,"leftOn":1668206653892,"userLeftFlag":true}},"name":"Yen-Xi LIN","isModerator":false,"isDialIn":false,"answers":{},"talk":{"totalTime":0,"lastTalkStartedOn":0},"emojis":[],"webcams":[],"totalOfMessages":2},"3549-2":{"userKey":"3549-2","extId":"3549","intIds":{"w_betjosq4tzr3":{"intId":"w_betjosq4tzr3","registeredOn":1668214892821,"leftOn":1668230215073,"userLeftFlag":false}},"name":"Wanxuan ZHANG","isModerator":false,"isDialIn":false,"answers":{},"talk":{"totalTime":0,"lastTalkStartedOn":0},"emojis":[],"webcams":[],"totalOfMessages":3},"3367-1":{"userKey":"3367-1","extId":"3367","intIds":{"w_o9itjkpbaeww":{"intId":"w_o9itjkpbaeww","registeredOn":1668213952303,"leftOn":1668222533893,"userLeftFlag":true},"w_taz0nfoaocwy":{"intId":"w_taz0nfoaocwy","registeredOn":1668222853852,"leftOn":1668225293892,"userLeftFlag":true},"w_rv0co9roq0fa":{"intId":"w_rv0co9roq0fa","registeredOn":1668226012598,"leftOn":1668229973892,"userLeftFlag":true},"w_mkwjtnmouk4u":{"intId":"w_mkwjtnmouk4u","registeredOn":1668203429571,"leftOn":1668203513892,"userLeftFlag":true},"w_3thxlxfd8lu1":{"intId":"w_3thxlxfd8lu1","registeredOn":1668222568598,"leftOn":1668222703892,"userLeftFlag":true}},"name":"Diana Marcela RUEDA BUENO","isModerator":false,"isDialIn":false,"answers":{},"talk":{"totalTime":0,"lastTalkStartedOn":0},"emojis":[],"webcams":[],"totalOfMessages":5},"3794-1":{"userKey":"3794-1","extId":"3794","intIds":{"w_iizou5pqrhqp":{"intId":"w_iizou5pqrhqp","registeredOn":1668209074431,"leftOn":1668209393893,"userLeftFlag":true},"w_3fn2zusfmxxt":{"intId":"w_3fn2zusfmxxt","registeredOn":1668220657415,"leftOn":1668220693892,"userLeftFlag":true},"w_qgf3d12yvpar":{"intId":"w_qgf3d12yvpar","registeredOn":1668225328276,"leftOn":1668225633893,"userLeftFlag":true},"w_wodducgljmcy":{"intId":"w_wodducgljmcy","registeredOn":1668225793348,"leftOn":1668226753893,"userLeftFlag":true}},"name":"Chia-Ying LIN","isModerator":false,"isDialIn":false,"answers":{},"talk":{"totalTime":0,"lastTalkStartedOn":0},"emojis":[],"webcams":[],"totalOfMessages":4},"3775-1":{"userKey":"3775-1","extId":"3775","intIds":{"w_qgrioypg31to":{"intId":"w_qgrioypg31to","registeredOn":1668213922312,"leftOn":1668213983892,"userLeftFlag":true},"w_jzhaek6rz7ln":{"intId":"w_jzhaek6rz7ln","registeredOn":1668217221208,"leftOn":1668219323893,"userLeftFlag":true},"w_jaxsihb9pypv":{"intId":"w_jaxsihb9pypv","registeredOn":1668210342323,"leftOn":1668213933892,"userLeftFlag":true},"w_vuesw2eduehv":{"intId":"w_vuesw2eduehv","registeredOn":1668206739324,"leftOn":1668210353892,"userLeftFlag":true},"w_cdfzqek9psd8":{"intId":"w_cdfzqek9psd8","registeredOn":1668226248832,"leftOn":1668226353892,"userLeftFlag":true},"w_q4fprjzmovm1":{"intId":"w_q4fprjzmovm1","registeredOn":1668219309587,"leftOn":1668220473893,"userLeftFlag":true},"w_wiqhvjeim3ku":{"intId":"w_wiqhvjeim3ku","registeredOn":1668222926237,"leftOn":1668225003892,"userLeftFlag":true}},"name":"Le Mai Han TRAN","isModerator":false,"isDialIn":false,"answers":{},"talk":{"totalTime":0,"lastTalkStartedOn":0},"emojis":[],"webcams":[],"totalOfMessages":10},"3438-1":{"userKey":"3438-1","extId":"3438","intIds":{"w_ntdhbfkaspv1":{"intId":"w_ntdhbfkaspv1","registeredOn":1668224697251,"leftOn":1668224843892,"userLeftFlag":true},"w_k3i9n4gpgonk":{"intId":"w_k3i9n4gpgonk","registeredOn":1668225796347,"leftOn":1668225903892,"userLeftFlag":true}},"name":"Hin Yeung POON","isModerator":false,"isDialIn":false,"answers":{},"talk":{"totalTime":0,"lastTalkStartedOn":0},"emojis":[],"webcams":[],"totalOfMessages":2}},"polls":{},"screenshares":[],"presentationSlides":[{"presentationId":"70572fdd6fa53e0a9bc837193d77e3b4dfafa412-1668202458879","pageNum":1,"setOn":1668202464477},{"presentationId":"26a697bace67b1ab21bcd7652b1c82d3ac01e2ec-1668202574666","pageNum":1,"setOn":1668202580740},{"presentationId":"26a697bace67b1ab21bcd7652b1c82d3ac01e2ec-1668202574666","pageNum":3,"setOn":1668202586884},{"presentationId":"26a697bace67b1ab21bcd7652b1c82d3ac01e2ec-1668202574666","pageNum":4,"setOn":1668202589370},{"presentationId":"26a697bace67b1ab21bcd7652b1c82d3ac01e2ec-1668202574666","pageNum":5,"setOn":1668203717804},{"presentationId":"26a697bace67b1ab21bcd7652b1c82d3ac01e2ec-1668202574666","pageNum":6,"setOn":1668203719576},{"presentationId":"8c2b1b18054371f507705a8cf84982e0f462e087-1668205984941","pageNum":1,"setOn":1668205993364},{"presentationId":"8c2b1b18054371f507705a8cf84982e0f462e087-1668205984941","pageNum":50,"setOn":1668206037279},{"presentationId":"8c2b1b18054371f507705a8cf84982e0f462e087-1668205984941","pageNum":51,"setOn":1668206039455},{"presentationId":"8c2b1b18054371f507705a8cf84982e0f462e087-1668205984941","pageNum":52,"setOn":1668206041052},{"presentationId":"8c2b1b18054371f507705a8cf84982e0f462e087-1668205984941","pageNum":53,"setOn":1668206042144},{"presentationId":"8c2b1b18054371f507705a8cf84982e0f462e087-1668205984941","pageNum":54,"setOn":1668206042802},{"presentationId":"8c2b1b18054371f507705a8cf84982e0f462e087-1668205984941","pageNum":55,"setOn":1668206043440},{"presentationId":"8c2b1b18054371f507705a8cf84982e0f462e087-1668205984941","pageNum":56,"setOn":1668206044117},{"presentationId":"8c2b1b18054371f507705a8cf84982e0f462e087-1668205984941","pageNum":57,"setOn":1668206044998},{"presentationId":"8c2b1b18054371f507705a8cf84982e0f462e087-1668205984941","pageNum":58,"setOn":1668206045779},{"presentationId":"8c2b1b18054371f507705a8cf84982e0f462e087-1668205984941","pageNum":59,"setOn":1668206047137},{"presentationId":"8c2b1b18054371f507705a8cf84982e0f462e087-1668205984941","pageNum":60,"setOn":1668206048622},{"presentationId":"8c2b1b18054371f507705a8cf84982e0f462e087-1668205984941","pageNum":61,"setOn":1668206049550},{"presentationId":"8c2b1b18054371f507705a8cf84982e0f462e087-1668205984941","pageNum":62,"setOn":1668206051556},{"presentationId":"8c2b1b18054371f507705a8cf84982e0f462e087-1668205984941","pageNum":63,"setOn":1668206052497},{"presentationId":"8c2b1b18054371f507705a8cf84982e0f462e087-1668205984941","pageNum":64,"setOn":1668206053371},{"presentationId":"8c2b1b18054371f507705a8cf84982e0f462e087-1668205984941","pageNum":65,"setOn":1668206054156},{"presentationId":"8c2b1b18054371f507705a8cf84982e0f462e087-1668205984941","pageNum":66,"setOn":1668206055368},{"presentationId":"8c2b1b18054371f507705a8cf84982e0f462e087-1668205984941","pageNum":67,"setOn":1668206057071},{"presentationId":"8c2b1b18054371f507705a8cf84982e0f462e087-1668205984941","pageNum":68,"setOn":1668206058270},{"presentationId":"8c2b1b18054371f507705a8cf84982e0f462e087-1668205984941","pageNum":69,"setOn":1668206060099},{"presentationId":"8c2b1b18054371f507705a8cf84982e0f462e087-1668205984941","pageNum":70,"setOn":1668206508976},{"presentationId":"8c2b1b18054371f507705a8cf84982e0f462e087-1668205984941","pageNum":71,"setOn":1668207299210},{"presentationId":"8c2b1b18054371f507705a8cf84982e0f462e087-1668205984941","pageNum":70,"setOn":1668207303298},{"presentationId":"8c2b1b18054371f507705a8cf84982e0f462e087-1668205984941","pageNum":71,"setOn":1668207304532},{"presentationId":"8c2b1b18054371f507705a8cf84982e0f462e087-1668205984941","pageNum":72,"setOn":1668207305362},{"presentationId":"8c2b1b18054371f507705a8cf84982e0f462e087-1668205984941","pageNum":71,"setOn":1668207307005},{"presentationId":"8c2b1b18054371f507705a8cf84982e0f462e087-1668205984941","pageNum":70,"setOn":1668207308814},{"presentationId":"4e410cdb3326439465c615eb4437cda17cdd28eb-1668207333096","pageNum":1,"setOn":1668207345648},{"presentationId":"4e410cdb3326439465c615eb4437cda17cdd28eb-1668207333096","pageNum":60,"setOn":1668207373686},{"presentationId":"4e410cdb3326439465c615eb4437cda17cdd28eb-1668207333096","pageNum":61,"setOn":1668207375960},{"presentationId":"4e410cdb3326439465c615eb4437cda17cdd28eb-1668207333096","pageNum":62,"setOn":1668207376933},{"presentationId":"4e410cdb3326439465c615eb4437cda17cdd28eb-1668207333096","pageNum":63,"setOn":1668207377820},{"presentationId":"4e410cdb3326439465c615eb4437cda17cdd28eb-1668207333096","pageNum":64,"setOn":1668210102238},{"presentationId":"4e410cdb3326439465c615eb4437cda17cdd28eb-1668207333096","pageNum":63,"setOn":1668210125727},{"presentationId":"4e410cdb3326439465c615eb4437cda17cdd28eb-1668207333096","pageNum":64,"setOn":1668210128724},{"presentationId":"4e410cdb3326439465c615eb4437cda17cdd28eb-1668207333096","pageNum":65,"setOn":1668213109561},{"presentationId":"4e410cdb3326439465c615eb4437cda17cdd28eb-1668207333096","pageNum":66,"setOn":1668213111074},{"presentationId":"4e410cdb3326439465c615eb4437cda17cdd28eb-1668207333096","pageNum":67,"setOn":1668213112722},{"presentationId":"26a697bace67b1ab21bcd7652b1c82d3ac01e2ec-1668202574666","pageNum":6,"setOn":1668217605678},{"presentationId":"26a697bace67b1ab21bcd7652b1c82d3ac01e2ec-1668202574666","pageNum":7,"setOn":1668217607265},{"presentationId":"8c2b1b18054371f507705a8cf84982e0f462e087-1668205984941","pageNum":70,"setOn":1668217715048},{"presentationId":"8c2b1b18054371f507705a8cf84982e0f462e087-1668205984941","pageNum":71,"setOn":1668217717850},{"presentationId":"8c2b1b18054371f507705a8cf84982e0f462e087-1668205984941","pageNum":72,"setOn":1668217719007},{"presentationId":"8c2b1b18054371f507705a8cf84982e0f462e087-1668205984941","pageNum":73,"setOn":1668217720580},{"presentationId":"8c2b1b18054371f507705a8cf84982e0f462e087-1668205984941","pageNum":74,"setOn":1668217723030},{"presentationId":"8c2b1b18054371f507705a8cf84982e0f462e087-1668205984941","pageNum":73,"setOn":1668217725087},{"presentationId":"8c2b1b18054371f507705a8cf84982e0f462e087-1668205984941","pageNum":72,"setOn":1668217728236},{"presentationId":"8c2b1b18054371f507705a8cf84982e0f462e087-1668205984941","pageNum":73,"setOn":1668217736473},{"presentationId":"8c2b1b18054371f507705a8cf84982e0f462e087-1668205984941","pageNum":74,"setOn":1668217737147},{"presentationId":"8c2b1b18054371f507705a8cf84982e0f462e087-1668205984941","pageNum":75,"setOn":1668217737667},{"presentationId":"8c2b1b18054371f507705a8cf84982e0f462e087-1668205984941","pageNum":76,"setOn":1668217738626},{"presentationId":"8c2b1b18054371f507705a8cf84982e0f462e087-1668205984941","pageNum":75,"setOn":1668217739467},{"presentationId":"8c2b1b18054371f507705a8cf84982e0f462e087-1668205984941","pageNum":74,"setOn":1668217741230},{"presentationId":"8c2b1b18054371f507705a8cf84982e0f462e087-1668205984941","pageNum":73,"setOn":1668217742846},{"presentationId":"8c2b1b18054371f507705a8cf84982e0f462e087-1668205984941","pageNum":74,"setOn":1668221847967},{"presentationId":"8c2b1b18054371f507705a8cf84982e0f462e087-1668205984941","pageNum":75,"setOn":1668221849391},{"presentationId":"8c2b1b18054371f507705a8cf84982e0f462e087-1668205984941","pageNum":76,"setOn":1668221857784},{"presentationId":"8c2b1b18054371f507705a8cf84982e0f462e087-1668205984941","pageNum":77,"setOn":1668221888545},{"presentationId":"8c2b1b18054371f507705a8cf84982e0f462e087-1668205984941","pageNum":78,"setOn":1668221889324},{"presentationId":"8c2b1b18054371f507705a8cf84982e0f462e087-1668205984941","pageNum":79,"setOn":1668221890264},{"presentationId":"8c2b1b18054371f507705a8cf84982e0f462e087-1668205984941","pageNum":80,"setOn":1668221891741},{"presentationId":"8c2b1b18054371f507705a8cf84982e0f462e087-1668205984941","pageNum":79,"setOn":1668221893143},{"presentationId":"8c2b1b18054371f507705a8cf84982e0f462e087-1668205984941","pageNum":78,"setOn":1668221893637},{"presentationId":"8c2b1b18054371f507705a8cf84982e0f462e087-1668205984941","pageNum":77,"setOn":1668221894182},{"presentationId":"8c2b1b18054371f507705a8cf84982e0f462e087-1668205984941","pageNum":76,"setOn":1668221896743},{"presentationId":"8c2b1b18054371f507705a8cf84982e0f462e087-1668205984941","pageNum":75,"setOn":1668221905713},{"presentationId":"8c2b1b18054371f507705a8cf84982e0f462e087-1668205984941","pageNum":76,"setOn":1668221909423},{"presentationId":"b02cc1e6e8dbec78d9b97f47d7366c678f087917-1668222123151","pageNum":1,"setOn":1668222133278},{"presentationId":"b02cc1e6e8dbec78d9b97f47d7366c678f087917-1668222123151","pageNum":2,"setOn":1668222137810},{"presentationId":"b02cc1e6e8dbec78d9b97f47d7366c678f087917-1668222123151","pageNum":3,"setOn":1668222140715},{"presentationId":"b02cc1e6e8dbec78d9b97f47d7366c678f087917-1668222123151","pageNum":4,"setOn":1668222148790},{"presentationId":"b02cc1e6e8dbec78d9b97f47d7366c678f087917-1668222123151","pageNum":3,"setOn":1668222151326},{"presentationId":"b02cc1e6e8dbec78d9b97f47d7366c678f087917-1668222123151","pageNum":2,"setOn":1668222152305},{"presentationId":"b02cc1e6e8dbec78d9b97f47d7366c678f087917-1668222123151","pageNum":3,"setOn":1668222157185},{"presentationId":"b02cc1e6e8dbec78d9b97f47d7366c678f087917-1668222123151","pageNum":2,"setOn":1668222206781},{"presentationId":"b02cc1e6e8dbec78d9b97f47d7366c678f087917-1668222123151","pageNum":1,"setOn":1668222207804},{"presentationId":"8c2b1b18054371f507705a8cf84982e0f462e087-1668205984941","pageNum":76,"setOn":1668226113326},{"presentationId":"8c2b1b18054371f507705a8cf84982e0f462e087-1668205984941","pageNum":77,"setOn":1668226116236},{"presentationId":"8c2b1b18054371f507705a8cf84982e0f462e087-1668205984941","pageNum":78,"setOn":1668226117432},{"presentationId":"8c2b1b18054371f507705a8cf84982e0f462e087-1668205984941","pageNum":79,"setOn":1668226118978},{"presentationId":"8c2b1b18054371f507705a8cf84982e0f462e087-1668205984941","pageNum":80,"setOn":1668226120695},{"presentationId":"8c2b1b18054371f507705a8cf84982e0f462e087-1668205984941","pageNum":79,"setOn":1668226123086},{"presentationId":"8c2b1b18054371f507705a8cf84982e0f462e087-1668205984941","pageNum":78,"setOn":1668226123836},{"presentationId":"8c2b1b18054371f507705a8cf84982e0f462e087-1668205984941","pageNum":79,"setOn":1668228610930},{"presentationId":"26a697bace67b1ab21bcd7652b1c82d3ac01e2ec-1668202574666","pageNum":7,"setOn":1668229940019},{"presentationId":"26a697bace67b1ab21bcd7652b1c82d3ac01e2ec-1668202574666","pageNum":9,"setOn":1668229942181}],"createdOn":1668202458880,"endedOn":1668230215073}